adslibraries/__init__.py
ads_libraries-0.2.3.dist-info/METADATA
ads_libraries-0.2.3.dist-info/WHEEL
ads_libraries-0.2.3.dist-info/entry_points.txt
ads_libraries-0.2.3.dist-info/top_level.txt
ads_libraries-0.2.3.dist-info/RECORD
