Metadata-Version: 2.1
Name: ads-libraries
Version: 0.2.3
Summary: adslibraries
Home-page: https://gitlab.astro.unige.ch/ferrigno/adslibraries
Author: C.F.
Author-email: carlo.ferrigno@unige.ch
License: MIT
Classifier: Development Status :: 4 - Beta
Classifier: Environment :: Console
Classifier: Intended Audience :: Science/Research
Classifier: License :: OSI Approved :: MIT License
Classifier: Operating System :: POSIX
Classifier: Programming Language :: Python :: 3.4
Classifier: Programming Language :: Python :: 3.5
Classifier: Programming Language :: Python :: 3.6
Classifier: Programming Language :: Python :: 3.7
Classifier: Programming Language :: Python :: 3.8
Classifier: Programming Language :: Python :: 3.9
Classifier: Programming Language :: Python :: 3.10
Classifier: Programming Language :: Python :: 3.11
Classifier: Topic :: Internet
Classifier: Topic :: Scientific/Engineering :: Astronomy
Requires-Dist: requests
Requires-Dist: unidecode
Requires-Dist: bibtexparser <=1.4.1
Requires-Dist: click
